[{"saintimage":"https://files.saint.gr/photos/standard/0626/OsiosDavid01s.jpg","saintname":"Όσιος Δαβίδ από τη Θεσσαλονίκη","link":"https://www.saint.gr/630/saint.aspx?#LiturgicalTexts"},{"saintimage":"/images/nophoto.png","saintname":"Όσιος Ιωάννης επίσκοπος Γοτθίας","link":"https://www.saint.gr/629/saint.aspx?#LiturgicalTexts"},{"saintimage":"/images/nophoto.png","saintname":"Όσιος Ανθίων","link":"https://www.saint.gr/628/saint.aspx?#LiturgicalTexts"},{"saintimage":"https://files.saint.gr/photos/standard/0626/AgiosDavidOsiomartiras01s.jpg","saintname":"Άγιος Δαβίδ ο νέος Οσιομάρτυρας","link":"https://www.saint.gr/627/saint.aspx?#LiturgicalTexts"},{"saintimage":"/images/nophoto.png","saintname":"Άγιοι Θεράπων, Μακάριος, Μάρκιος και Μαρκία","link":"https://www.saint.gr/626/saint.aspx?#LiturgicalTexts"},{"saintimage":"/images/nophoto.png","saintname":"Εγκαίνια ναού Αγίου Θεοδώρου «ἐν τῷ Ῥησίῳ»","link":"https://www.saint.gr/2901/saint.aspx?#LiturgicalTexts"},{"saintimage":"/images/nophoto.png","saintname":"Άγιος Διονύσιος Αρχιεπίσκοπος Σουζδαλίας","link":"https://www.saint.gr/3368/saint.aspx?#LiturgicalTexts"},{"saintname":"","link":"https://www.saint.grundefined?#LiturgicalTexts"}]