[{"saintimage":"https://files.saint.gr/filesnew/02/0598/photos/Pentecosti04s.jpg","saintname":"Κυριακή της Πεντηκοστής","link":"https://www.saint.gr/598/saint.aspx?#LiturgicalTexts"},{"saintimage":"https://files.saint.gr/filesnew/04/1943/photos/AgiosMethodios02s.jpg","saintname":"Άγιος Μεθόδιος ο Ιερομάρτυρας επίσκοπος Πατάρων","link":"https://www.saint.gr/1943/saint.aspx?#LiturgicalTexts"},{"saintimage":"https://files.saint.gr/photos/standard/0620/AgiosNikolaosKavasilas01s.jpg","saintname":"Άγιος Νικόλαος ο Καβάσιλας","link":"https://www.saint.gr/1947/saint.aspx?#LiturgicalTexts"},{"saintimage":"https://files.saint.gr/photos/standard/0620/OsiosKallistos01s.jpg","saintname":"Όσιος Κάλλιστος Πατριάρχης Κωνσταντινούπολης","link":"https://www.saint.gr/1946/saint.aspx?#LiturgicalTexts"},{"saintimage":"/images/nophoto.png","saintname":"Κατάθεσις των Ιερών Λειψάνων και Περιβολαίων των Αγίων Αποστόλων Λουκά....","link":"https://www.saint.gr/1944/saint.aspx?#LiturgicalTexts"},{"saintimage":"/images/nophoto.png","saintname":"Άγιοι Δύο Ασκητές","link":"https://www.saint.gr/1945/saint.aspx?#LiturgicalTexts"},{"saintimage":"https://files.saint.gr/photos/standard/0620/PanagiaOdigitria01s.jpg","saintname":"Σύναξη της Υπεραγίας Θεοτόκου της Οδηγήτριας","link":"https://www.saint.gr/1948/saint.aspx?#LiturgicalTexts"},{"saintimage":"/images/nophoto.png","saintname":"Όσιος Αθανάσιος ο θαυματουργός ο Πεντασχινίτης Κύπρου","link":"https://www.saint.gr/1949/saint.aspx?#LiturgicalTexts"}]