[{"saintimage":"https://files.saint.gr/filesnew/02/0732/photos/ProphitisIlias09s.jpg","saintname":"Προφήτης Ηλίας ο Θεσβίτης","link":"https://www.saint.gr/732/saint.aspx?#LiturgicalTexts"},{"saintimage":"/images/nophoto.png","saintname":"Ανάμνηση των εγκαινίων του Ναού του Τιμίου Προδρόμου της Μονής Στουδίο....","link":"https://www.saint.gr/731/saint.aspx?#LiturgicalTexts"},{"saintimage":"/images/nophoto.png","saintname":"Όσιος Αβραάμ του Κουκχλόμα","link":"https://www.saint.gr/3367/saint.aspx?#LiturgicalTexts"},{"saintimage":"https://files.saint.gr/photos/standard/0720/OsiosAthanasiosBrest01s.jpg","saintname":"Ανακομιδή Ιερών Λειψάνων του Αγίου Αθανασίου ηγουμένου της Μονής Μπρέσ....","link":"https://www.saint.gr/871/saint.aspx?#LiturgicalTexts"},{"saintimage":"https://files.saint.gr/filesnew/09/4381/photos/AgioiRosoiMartyresParisi03s.jpg","saintname":"Σύναξη των Ρώσων αγίων των εν Γαλλία τελειωθέντων","link":"https://www.saint.gr/4381/saint.aspx?#LiturgicalTexts"},{"saintname":"","link":"https://www.saint.grundefined?#LiturgicalTexts"},{"saintname":"","link":"https://www.saint.grundefined?#LiturgicalTexts"},{"saintname":"","link":"https://www.saint.grundefined?#LiturgicalTexts"}]