[{"saintimage":"https://files.saint.gr/photos/standard/0912/AgiosAutonomos01s.jpg","saintname":"Άγιος Αυτόνομος","link":"https://www.saint.gr/2409/saint.aspx?#LiturgicalTexts"},{"saintimage":"https://files.saint.gr/photos/standard/0912/AgiosKornoutosIkoniou01s.jpg","saintname":"Άγιος Κουρνούτος ο Ιερομάρτυρας επίσκοπος Ικονίου","link":"https://www.saint.gr/2410/saint.aspx?#LiturgicalTexts"},{"saintimage":"/images/nophoto.png","saintname":"Άγιος Ιουλιανός ο πρεσβύτερος Αγκύρας από τη Γαλατία","link":"https://www.saint.gr/2412/saint.aspx?#LiturgicalTexts"},{"saintimage":"/images/nophoto.png","saintname":"Άγιος Θεόδωρος ο Ιερομάρτυρας, επίσκοπος Αλεξανδρείας","link":"https://www.saint.gr/2411/saint.aspx?#LiturgicalTexts"},{"saintimage":"/images/nophoto.png","saintname":"Άγιοι Μακεδόνιος, Θεόδουλος και Τατιανός","link":"https://www.saint.gr/2413/saint.aspx?#LiturgicalTexts"},{"saintimage":"https://files.saint.gr/photos/standard/0912/OsiosDaniilThasos01s.jpg","saintname":"Όσιος Δανιήλ ο Θάσιος","link":"https://www.saint.gr/2414/saint.aspx?#LiturgicalTexts"},{"saintimage":"/images/nophoto.png","saintname":"Άγιος Ωκεανός","link":"https://www.saint.gr/2415/saint.aspx?#LiturgicalTexts"},{"saintimage":"https://files.saint.gr/photos/standard/0912/AgiosKornoutas01s.jpg","saintname":"Άγιος Κουρνούτας ο εν την Αχεράν ασκήσας","link":"https://www.saint.gr/4288/saint.aspx?#LiturgicalTexts"},{"saintimage":"/images/nophoto.png","saintname":"Άγιος Ανδρόνικος «ὁ ἐν τὴ Ἀτρώα»","link":"https://www.saint.gr/2416/saint.aspx?#LiturgicalTexts"},{"saintimage":"/images/nophoto.png","saintname":"Άγιος Albeus","link":"https://www.saint.gr/2417/saint.aspx?#LiturgicalTexts"},{"saintimage":"/images/nophoto.png","saintname":"Ανάμνηση αφωνίας και όρασης του Ζαχαρία","link":"https://www.saint.gr/2418/saint.aspx?#LiturgicalTexts"},{"saintimage":"https://files.saint.gr/filesnew/05/2408/photos/AgioiNeomartyresMikrasAsias01s.jpg","saintname":"Άγιος Χρυσόστομος Σμύρνης και οι συν αυτώ Άγιοι Αρχιερείς Γρηγόριος Κυ....","link":"https://www.saint.gr/2408/saint.aspx?#LiturgicalTexts"}]