[{"saintimage":"https://files.saint.gr/photos/standard/0923/AgiosIoannisSilipsi01s.jpg","saintname":"Άγιος Ιωάννης Πρόδρομος και Βαπτιστής (Σύλληψη)","link":"https://www.saint.gr/2329/saint.aspx?#LiturgicalTexts"},{"saintimage":"https://files.saint.gr/photos/standard/0923/AgiosNikolaos01s.jpg","saintname":"Άγιος Νικόλαος ο παντοπώλης ο Νεομάρτυρας από το Καρπενήσι","link":"https://www.saint.gr/2334/saint.aspx?#LiturgicalTexts"},{"saintimage":"/images/nophoto.png","saintname":"Άγιος Ανδρέας","link":"https://www.saint.gr/2330/saint.aspx?#LiturgicalTexts"},{"saintimage":"/images/nophoto.png","saintname":"Άγιος Ιωάννης με τα δύο παιδιά του Πέτρο και Αντώνιο","link":"https://www.saint.gr/2331/saint.aspx?#LiturgicalTexts"},{"saintimage":"https://files.saint.gr/photos/standard/0923/AgiaRhais02s.jpg","saintname":"Αγία Ραΐς η παρθένος","link":"https://www.saint.gr/2332/saint.aspx?#LiturgicalTexts"},{"saintimage":"https://files.saint.gr/photos/standard/0923/OsiesXanthipiPolixeni01s.jpg","saintname":"Οσίες Ξανθίππη και Πολυξένη","link":"https://www.saint.gr/2333/saint.aspx?#LiturgicalTexts"},{"saintimage":"https://files.saint.gr/photos/standard/0923/AgiosIoannisEksOthomanon01s.jpg","saintname":"Άγιος Ιωάννης ο Νεομάρτυρας ο εξ Αγαρηνών","link":"https://www.saint.gr/2335/saint.aspx?#LiturgicalTexts"},{"saintimage":"/images/nophoto.png","saintname":"Άγιος Γρηγόριος Μητροπολίτης Άργους","link":"https://www.saint.gr/2337/saint.aspx?#LiturgicalTexts"},{"saintimage":"/images/nophoto.png","saintname":"Άγιος Adamnan","link":"https://www.saint.gr/2336/saint.aspx?#LiturgicalTexts"},{"saintname":"","link":"https://www.saint.grundefined?#LiturgicalTexts"},{"saintname":"","link":"https://www.saint.grundefined?#LiturgicalTexts"},{"saintname":"","link":"https://www.saint.grundefined?#LiturgicalTexts"}]