[{"saintimage":"https://files.saint.gr/filesnew/06/2914/photos/AgioiGouriasSamonasAbibos01s.jpg","saintname":"Άγιοι Γουρίας, Σαμωνάς και Άβιβος οι Ομολογητές","link":"https://www.saint.gr/2914/saint.aspx?#LiturgicalTexts"},{"saintimage":"/images/nophoto.png","saintname":"Άγιοι Ελπίδιος, Μάρκελλος και Ευστόχιος","link":"https://www.saint.gr/2917/saint.aspx?#LiturgicalTexts"},{"saintimage":"/images/nophoto.png","saintname":"Όσιος Κυντίων επίσκοπος Σελευκείας","link":"https://www.saint.gr/2915/saint.aspx?#LiturgicalTexts"},{"saintimage":"/images/nophoto.png","saintname":"Άγιοι Ιουστίνος και Θεοδώρα οι ευσεβείς βασιλείς","link":"https://www.saint.gr/2916/saint.aspx?#LiturgicalTexts"},{"saintimage":"/images/nophoto.png","saintname":"Άγιος Δημήτριος","link":"https://www.saint.gr/2918/saint.aspx?#LiturgicalTexts"},{"saintimage":"/images/nophoto.png","saintname":"Άγιοι Ευψύχιος, Νέαρχος και Καρτέριος","link":"https://www.saint.gr/2919/saint.aspx?#LiturgicalTexts"},{"saintimage":"/images/nophoto.png","saintname":"Άγιος Θωμάς ο Β' ο νέος, Πατριάρχης Κωνσταντινούπολης","link":"https://www.saint.gr/168/saint.aspx?#LiturgicalTexts"},{"saintimage":"https://files.saint.gr/photos/standard/1115/OsiosPaisiosVelichkovsky01s.jpg","saintname":"Όσιος Παΐσιος Βελιτσκόφσκυ","link":"https://www.saint.gr/2920/saint.aspx?#LiturgicalTexts"}]